[
  {
    "timestamp": "2025-05-23T19:10:58.109536",
    "machine_id": "R-A0T",
    "temperature": 78.94,
    "vibration": 1.07,
    "rpm": 2730,
    "pressure": 6.13,
    "humidity": 39.58,
    "voltage": 247.7,
    "failure": 0
  },
  {
    "timestamp": "2025-05-23T19:10:58.109593",
    "machine_id": "J-Z28",
    "temperature": 72.68,
    "vibration": 1.35,
    "rpm": 2666,
    "pressure": 4.92,
    "humidity": 40.56,
    "voltage": 210.62,
    "failure": 0
  },
  {
    "timestamp": "2025-05-23T19:10:58.109604",
    "machine_id": "N-BR5",
    "temperature": 67.01,
    "vibration": 2.09,
    "rpm": 2532,
    "pressure": 6.36,
    "humidity": 30.51,
    "voltage": 217.4,
    "failure": 0
  },
  {
    "timestamp": "2025-05-23T19:10:58.109609",
    "machine_id": "M-2G0",
    "temperature": 73.25,
    "vibration": 1.72,
    "rpm": 2882,
    "pressure": 6.4,
    "humidity": 65.72,
    "voltage": 248.75,
    "failure": 0
  },
  {
    "timestamp": "2025-05-23T19:10:58.109614",
    "machine_id": "B-3OR",
    "temperature": 97.13,
    "vibration": 2.18,
    "rpm": 2767,
    "pressure": 3.94,
    "humidity": 59.59,
    "voltage": 234.1,
    "failure": 0
  },
  {
    "timestamp": "2025-05-23T19:10:58.109620",
    "machine_id": "C-SGE",
    "temperature": 76.91,
    "vibration": 0.81,
    "rpm": 2779,
    "pressure": 5.26,
    "humidity": 64.54,
    "voltage": 239.72,
    "failure": 0
  },
  {
    "timestamp": "2025-05-23T19:10:58.109625",
    "machine_id": "N-PR7",
    "temperature": 62.59,
    "vibration": 1.7,
    "rpm": 3054,
    "pressure": 5.5,
    "humidity": 42.49,
    "voltage": 243.45,
    "failure": 0
  },
  {
    "timestamp": "2025-05-23T19:10:58.109631",
    "machine_id": "M-TZ4",
    "temperature": 97.15,
    "vibration": 0.73,
    "rpm": 2806,
    "pressure": 7.16,
    "humidity": 56.43,
    "voltage": 212.35,
    "failure": 0
  },
  {
    "timestamp": "2025-05-23T19:10:58.109635",
    "machine_id": "L-U6X",
    "temperature": 75.62,
    "vibration": 1.25,
    "rpm": 3026,
    "pressure": 7.13,
    "humidity": 35.34,
    "voltage": 227.27,
    "failure": 1
  },
  {
    "timestamp": "2025-05-23T19:10:58.109638",
    "machine_id": "E-8KR",
    "temperature": 79.88,
    "vibration": 0.61,
    "rpm": 2939,
    "pressure": 7.14,
    "humidity": 58.75,
    "voltage": 229.76,
    "failure": 0
  }
]