[
  {
    "timestamp": "2025-05-23T19:13:59.155754",
    "machine_id": "I-4ZH",
    "temperature": 92.78,
    "vibration": 1.63,
    "rpm": 2910,
    "pressure": 7.15,
    "humidity": 62.09,
    "voltage": 235.1,
    "failure": 0,
    "note": NaN,
    "anomaly_details": {
      "temperature": "\u0394 17.85 > 15.0"
    }
  },
  {
    "timestamp": "2025-05-23T19:13:59.155760",
    "machine_id": "L-U6X",
    "temperature": 72.49,
    "vibration": 1.03,
    "rpm": 2613,
    "pressure": 7.45,
    "humidity": 30.82,
    "voltage": 227.23,
    "failure": 0,
    "note": NaN,
    "anomaly_details": {
      "temperature": "\u0394 20.29 > 15.0"
    }
  },
  {
    "timestamp": "2025-05-23T19:13:59.155766",
    "machine_id": "F-TR1",
    "temperature": 71.26,
    "vibration": 0.53,
    "rpm": 3031,
    "pressure": 3.6,
    "humidity": 31.34,
    "voltage": 244.7,
    "failure": 0,
    "note": NaN,
    "anomaly_details": {
      "voltage": "\u0394 17.47 > 15",
      "pressure": "\u0394 3.85 > 3.0"
    }
  },
  {
    "timestamp": "2025-05-23T19:13:59.155772",
    "machine_id": "W-NW7",
    "temperature": 84.59,
    "vibration": 0.81,
    "rpm": 2629,
    "pressure": 3.93,
    "humidity": 65.36,
    "voltage": 214.26,
    "failure": 1,
    "note": NaN,
    "anomaly_details": {
      "voltage": "\u0394 30.44 > 15"
    }
  },
  {
    "timestamp": "2025-05-23T19:13:59.155777",
    "machine_id": "G-09B",
    "temperature": 93.63,
    "vibration": 1.92,
    "rpm": 2690,
    "pressure": 5.33,
    "humidity": 67.29,
    "voltage": 230.27,
    "failure": 0,
    "note": NaN,
    "anomaly_details": {
      "vibration": "\u0394 1.11 > 1.0",
      "voltage": "\u0394 16.01 > 15"
    }
  }
]